{
  "parent": "minecraft:recipes/root",
  "criteria": {
    "has_exposed_copper_trapdoor": {
      "conditions": {
        "items": [
          {
            "items": [
              "oem:exposed_copper_trapdoor"
            ]
          }
        ]
      },
      "trigger": "minecraft:inventory_changed"
    },
    "has_the_recipe": {
      "conditions": {
        "recipe": "oem:waxed_exposed_copper_trapdoor"
      },
      "trigger": "minecraft:recipe_unlocked"
    }
  },
  "requirements": [
    [
      "has_exposed_copper_trapdoor",
      "has_the_recipe"
    ]
  ],
  "rewards": {
    "recipes": [
      "oem:waxed_exposed_copper_trapdoor"
    ]
  }
}